volga/fields.py
volga/format.py
volga/json.py
volga/schema.py
volga/types.py
volga-0.2.0.dist-info/LICENSE
volga-0.2.0.dist-info/WHEEL
volga-0.2.0.dist-info/METADATA
volga-0.2.0.dist-info/RECORD
