Metadata-Version: 2.1
Name: volga
Version: 0.2.0
Summary: A python framework for deserialization
Home-page: https://github.com/yefrig/volga
License: MIT
Keywords: python,serialize,deserialize
Author: Yefri Gaitan
Author-email: yefrigaitan@gmail.com
Requires-Python: >=3.9,<4.0
Classifier: Development Status :: 1 - Planning
Classifier: Intended Audience :: Developers
Classifier: License :: OSI Approved :: MIT License
Classifier: Operating System :: OS Independent
Classifier: Programming Language :: Python :: 3
Classifier: Programming Language :: Python :: 3.9
Classifier: Typing :: Typed
Project-URL: Repository, https://github.com/yefrig/volga
